4_bit_series_register.v
module reg_4bit(clk,clr,A,Y);
    input clk;
    input clr;
    input A;
    output reg Y;

reg B,C,D;
always @(posedge clk or negedge clr) 
 begin
    if(!clr) 
     begin 
        B <= 0; 
        C <= 0; 
        D <= 0; 
        Y <= 0; 
     end

    else 
     begin 
        Y <= D;
        D <= C;
        C <= B;
        B <= A;
     end
 end

endmodule

4_bit_series_register_TB.v
`include "4_bit_series_register.v"
module reg_4bit_test;
    reg clk, clr, in; wire out;
    reg_4bit SR(.clk(clk), .clr(clr), .A(in), .Y(out));
    initial
     begin
        clk = 1'b0; #2 clr = 1'b0; #5 clr =1'b1; 
     end
    always #5 clk = ~clk;
    initial
     begin #2
        repeat (4)
         begin 
            #10 in=0;
            #10 in=0;
            #10 in=1;
            #10 in=1;
         end
     end    
    initial
     begin
        $dumpfile("4_bit_series_register.vcd");
        $dumpvars(0, reg_4bit_test);
        #200 $finish;
     end

endmodule

build/4_bit_series_register.vcd
$date
	Wed Feb 12 23:13:50 2025
$end
$version
	Icarus Verilog
$end
$timescale
	1s
$end
$scope module reg_4bit_test $end
$var wire 1 ! out $end
$var reg 1 " clk $end
$var reg 1 # clr $end
$var reg 1 $ in $end
$scope module SR $end
$var wire 1 $ A $end
$var wire 1 " clk $end
$var wire 1 # clr $end
$var reg 1 % B $end
$var reg 1 & C $end
$var reg 1 ' D $end
$var reg 1 ! Y $end
$upscope $end
$upscope $end
$enddefinitions $end
$comment Show the parameter values. $end
$dumpall
$end
#0
$dumpvars
x'
x&
x%
x$
x#
0"
x!
$end
#2
0!
0'
0&
0%
0#
#5
1"
#7
1#
#10
0"
#12
0$
#15
1"
#20
0"
#25
1"
#30
0"
#32
1$
#35
1%
1"
#40
0"
#45
1&
1"
#50
0"
#52
0$
#55
0%
1'
1"
#60
0"
#65
0&
1!
1"
#70
0"
#72
1$
#75
1%
0'
1"
#80
0"
#85
1&
0!
1"
#90
0"
#92
0$
#95
0%
1'
1"
#100
0"
#105
0&
1!
1"
#110
0"
#112
1$
#115
1%
0'
1"
#120
0"
#125
1&
0!
1"
#130
0"
#132
0$
#135
0%
1'
1"
#140
0"
#145
0&
1!
1"
#150
0"
#152
1$
#155
1%
0'
1"
#160
0"
#165
1&
0!
1"
#170
0"
#175
1'
1"
#180
0"
#185
1!
1"
