full_adder.v
module half_adder(a, b, s, c);
  input a;
  input b;
  output s;
  output c;
  
  assign s = a^b;
  assign c = a&b;
  
endmodule

module full_adder(a,b,Cin, s, Cout);
  input a;
  input b;
  input Cin;
  output s;
  output Cout;
  wire t1, t2, t3;
  
  half_adder M0(a, b, t1, t2);
  half_adder M1(t1, Cin, s, t3);
  assign Cout = t2 | t3;
    
endmodule

full_adderTB.v
`include "full_adder.v"
`timescale 10ns/1ns
module F_A_test();

reg A; reg B; reg Ci; wire S; wire Co;

full_adder M(.a(A), .b(B), .Cin(Ci), .s(S), .Cout(Co));

initial begin
    $dumpfile("full_adder.vcd");
    $dumpvars(0, F_A_test);
    $monitor($time, "A=%b, B=%b, Ci=%b, S=%b, Co=%b", A,B,Ci,S,Co);
    #5 A = 1'b0; B=1'b0; Ci=1'b0;
    #5 A = 1'b0; B=1'b0; Ci=1'b1;
    #5 A = 1'b0; B=1'b1; Ci=1'b0;
    #5 A = 1'b0; B=1'b1; Ci=1'b1;
    #5 A = 1'b1; B=1'b0; Ci=1'b0;
    #5 A = 1'b1; B=1'b0; Ci=1'b1;
    #5 A = 1'b1; B=1'b1; Ci=1'b0;
    #5 A = 1'b1; B=1'b1; Ci=1'b1;
    #5 $finish;
end

endmodule

build/full_adder.vcd
$date
	Fri Jan 24 19:34:22 2025
$end
$version
	Icarus Verilog
$end
$timescale
	1ns
$end
$scope module F_A_test $end
$var wire 1 ! S $end
$var wire 1 " Co $end
$var reg 1 # A $end
$var reg 1 $ B $end
$var reg 1 % Ci $end
$scope module M $end
$var wire 1 % Cin $end
$var wire 1 " Cout $end
$var wire 1 # a $end
$var wire 1 $ b $end
$var wire 1 & t3 $end
$var wire 1 ' t2 $end
$var wire 1 ( t1 $end
$var wire 1 ! s $end
$scope module M0 $end
$var wire 1 # a $end
$var wire 1 $ b $end
$var wire 1 ' c $end
$var wire 1 ( s $end
$upscope $end
$scope module M1 $end
$var wire 1 ( a $end
$var wire 1 % b $end
$var wire 1 & c $end
$var wire 1 ! s $end
$upscope $end
$upscope $end
$upscope $end
$enddefinitions $end
$comment Show the parameter values. $end
$dumpall
$end
#0
$dumpvars
x(
x'
x&
x%
x$
x#
x"
x!
$end
#50
0"
0!
0&
0(
0'
0%
0$
0#
#100
1!
1%
#150
1(
0%
1$
#200
1"
0!
1&
1%
#250
0"
1!
0&
0%
0$
1#
#300
1"
0!
1&
1%
#350
0&
0(
1'
0%
1$
#400
1!
1%
